Justipy/Justipy.py
Justipy/__init__.py
Justipy-0.0.6.dist-info/LICENSE
Justipy-0.0.6.dist-info/METADATA
Justipy-0.0.6.dist-info/WHEEL
Justipy-0.0.6.dist-info/top_level.txt
Justipy-0.0.6.dist-info/RECORD
