Metadata-Version: 2.1
Name: Justipy
Version: 0.0.6
Summary: This package is used to write justified or centralized text to images.
Home-page: https://github.com/GustavoDenobi/Justipy
Author: GustavoDenobi
Author-email: gustavodenobi@gmail.com
License: UNKNOWN
Platform: UNKNOWN
Classifier: Programming Language :: Python :: 3
Classifier: License :: OSI Approved :: MIT License
Classifier: Operating System :: OS Independent
Requires-Python: >=3.6
